sparse_decomposition/__init__.py
sparse_decomposition-0.1.0.dist-info/AUTHORS.rst
sparse_decomposition-0.1.0.dist-info/LICENSE
sparse_decomposition-0.1.0.dist-info/METADATA
sparse_decomposition-0.1.0.dist-info/WHEEL
sparse_decomposition-0.1.0.dist-info/top_level.txt
sparse_decomposition-0.1.0.dist-info/RECORD
